{
  "$schema": "https://json-schema.org/draft/2020-12/schema",
  "$id": "https://github.com/OTOJulian/oto-hybrid-framework/schema/sync-allowlist.json",
  "type": "object",
  "required": ["version", "oto_owned_globs", "oto_diverged_paths"],
  "additionalProperties": false,
  "properties": {
    "version": { "type": "string", "const": "1" },
    "oto_owned_globs": {
      "type": "array",
      "minItems": 1,
      "items": { "type": "string", "minLength": 1 }
    },
    "oto_diverged_paths": {
      "type": "array",
      "items": { "type": "string", "minLength": 1 }
    }
  }
}
